assertion/SVA_Methods/countones/countones.sv
module countones;  
bit clk,a;  
logic [4:0] b;  

always #5 clk = ~clk; //clock generation  

initial begin
      a=0; b=5'b00000;
  #15 a=1; b=5'b001x0;  //15
  #10 a=0; b=5'b01000;  //25
  #10 a=1; b=5'b11011;  //35
  #10 a=0; b=5'b01000;  //45
  #10 a=1; b=5'b10xz0;  //55
  #10 a=0; b=5'b10000;  //65
  #10 a=1; b=5'bxxxxx;  //75
  #10 a=0; b=5'b01100;  //85
  #10 a=1; b=5'bzzzzz;  //95
  #10 a=0; b=5'b01000;  //105
  #10 a=1; b=5'b11110;  //115
  #10 a=0; b=5'b01000;  //125
  #10 a=1; b=5'b10000;  //135
  #10 a=1; b=5'b00100;  //145
  #10;
  $finish;
end

//property definition  
  property p;  
    @(posedge clk) a |-> ($countones(b)==1);  
  endproperty  
                      
//calling  assert property  
    a_1: assert property(p)  
       $info("Pass");  
    else  
       $info("Fail");  

    initial begin
       $dumpfile("waveform.vcd");
       $dumpvars();
    end
endmodule

assertion/SVA_Methods/countones/waveform.vcd
$date
	Tue Oct 11 01:49:07 2022
$end

$version
	Synopsys VCS version Q-2020.03-SP2-8_Full64
$end

$timescale
	1s
$end

$comment Csum: 1 83fc96d3e9588ee3 $end


$scope module countones $end
$var reg 1 ! a $end
$var reg 5 " b [4:0] $end
$var reg 1 # clk $end

$scope task _$$txp______assert_a_1 $end
$upscope $end


$scope task _$$txp_pass_action_a_1 $end
$upscope $end


$scope task _$$txp_fail_action_a_1 $end
$upscope $end

$upscope $end

$enddefinitions $end

#0
$dumpvars
0!
0#
b00000 "
$end
#5
1#
#10
0#
#15
1!
b001x0 "
1#
#20
0#
#25
0!
b01000 "
1#
#30
0#
#35
1!
b11011 "
1#
#40
0#
#45
0!
b01000 "
1#
#50
0#
#55
1!
b10xz0 "
1#
#60
0#
#65
0!
b10000 "
1#
#70
0#
#75
1!
bxxxxx "
1#
#80
0#
#85
0!
b01100 "
1#
#90
0#
#95
1!
bzzzzz "
1#
#100
0#
#105
0!
b01000 "
1#
#110
0#
#115
1!
b11110 "
1#
#120
0#
#125
0!
b01000 "
1#
#130
0#
#135
1!
b10000 "
1#
#140
0#
#145
b00100 "
1#
