assertion/SVA_Methods/past/past.sv
module past;  
bit clk,a,b;  

always #5 clk = ~clk; //clock generation  

initial begin
  a=0; b=0;
  #15 a=1; b=1;  //15
  #10 a=0; b=0;  //25
  #10 a=1; b=1;  //35
  #10 a=0; b=0;  //45
  #10 a=1; b=1;  //55
  #10 a=0; b=0;  //65
  #10 a=1; b=1;  //75
  #10 a=1; b=1;  //85
  #10 a=1; b=0;  //95
  #10 a=0; b=0;  //105
  #10 a=1; b=0;  //115
  #10 a=0; b=0;  //125
  #10 a=1; b=0;  //135
  #10 a=1; b=0;  //145
  #10;
  $finish;
end

//property definition  
property p;  
  @(posedge clk) a |-> ($past(b,2) == 1);  
endproperty  

//calling assert property  
a_1: assert property(p)  
$info("Pass");  
else  
  $info("Fail");  

  initial begin
    $dumpfile("waveform.vcd");
    $dumpvars();
  end
  endmodule

assertion/SVA_Methods/past/waveform.vcd
$date
	Tue Oct 11 02:09:38 2022
$end

$version
	Synopsys VCS version Q-2020.03-SP2-8_Full64
$end

$timescale
	1s
$end

$comment Csum: 1 c25f5a943f664ab7 $end


$scope module past $end
$var reg 1 ! a $end
$var reg 1 " clk $end
$var reg 1 # b $end

$scope task _$$txp______assert_a_1 $end
$upscope $end


$scope task _$$txp_pass_action_a_1 $end
$upscope $end


$scope task _$$txp_fail_action_a_1 $end
$upscope $end

$upscope $end

$enddefinitions $end

#0
$dumpvars
0!
0#
0"
$end
#5
1"
#10
0"
#15
1!
1#
1"
#20
0"
#25
0!
0#
1"
#30
0"
#35
1!
1#
1"
#40
0"
#45
0!
0#
1"
#50
0"
#55
1!
1#
1"
#60
0"
#65
0!
0#
1"
#70
0"
#75
1!
1#
1"
#80
0"
#85
1"
#90
0"
#95
0#
1"
#100
0"
#105
0!
1"
#110
0"
#115
1!
1"
#120
0"
#125
0!
1"
#130
0"
#135
1!
1"
