assertion/SVA_Methods/isunknown/isunknown.sv
module isunknown;  
  //declared variable to generate diffrents values
  bit clk,a;  
  logic [4:0] b;  
  
  //clock generation
  always #5 clk = ~clk;   
  
  //generating a and b
  initial begin
    //generating b values as 5 bits because this method bit by bit it will chek
    a=0; b=5'b00000;
    #15 a=1; b=5'b001x0;  //15
    #10 a=0; b=5'b01000;  //25
    #10 a=1; b=5'b010z0;  //35
    #10 a=0; b=5'b01000;  //45
    #10 a=1; b=5'b10xz0;  //55
    #10 a=0; b=5'b10000;  //65
    #10 a=1; b=5'bxxxxx;  //75
    #10 a=0; b=5'b01100;  //85
    #10 a=1; b=5'bzzzzz;  //95
    #10 a=0; b=5'b01000;  //105
    #10 a=1; b=5'b10100;  //115
    #10 a=0; b=5'b01000;  //125
    #10 a=1; b=5'b10000;  //135
    #10 a=1; b=5'b00100;  //145
    // Wait for 10 time units before terminating the simulation
    #10;
    // End the simulation
    $finish;
  end
  
  //property includes a and $isunknown(b) using overlapped implication operator
  property p;
    // Property holds true when the a aseerted and same clock any bit of b is X or Z     
    @(posedge clk) a |-> $isunknown(b);  
  endproperty  
 
  //calling assert property
  a_1: assert property(p)
         $info("pass");
       else
         $info("fail");

  // Initial block to generate waveform dump for simulation
  initial begin
    $dumpfile("waveform.vcd");
    $dumpvars();
  end  
endmodule

assertion/SVA_Methods/isunknown/waveform.vcd
$date
	Tue Oct 11 01:43:06 2022
$end

$version
	Synopsys VCS version Q-2020.03-SP2-8_Full64
$end

$timescale
	1s
$end

$comment Csum: 1 3839dd230bdba3b6 $end


$scope module isunknown $end
$var reg 1 ! a $end
$var reg 5 " b [4:0] $end
$var reg 1 # clk $end

$scope task _$$txp______assert_a_1 $end
$upscope $end


$scope task _$$txp_pass_action_a_1 $end
$upscope $end


$scope task _$$txp_fail_action_a_1 $end
$upscope $end

$upscope $end

$enddefinitions $end

#0
$dumpvars
0!
0#
b00000 "
$end
#5
1#
#10
0#
#15
1!
b001x0 "
1#
#20
0#
#25
0!
b01000 "
1#
#30
0#
#35
1!
b010z0 "
1#
#40
0#
#45
0!
b01000 "
1#
#50
0#
#55
1!
b10xz0 "
1#
#60
0#
#65
0!
b10000 "
1#
#70
0#
#75
1!
bxxxxx "
1#
#80
0#
#85
0!
b01100 "
1#
#90
0#
#95
1!
bzzzzz "
1#
#100
0#
#105
0!
b01000 "
1#
#110
0#
#115
1!
b10100 "
1#
#120
0#
#125
0!
b01000 "
1#
#130
0#
#135
1!
b10000 "
1#
#140
0#
#145
b00100 "
1#
