assertion/repetition_operators/goto_repetition/goto_repetition.sv
module goto_repetition;
  //declared variable to generate diffrents values
  bit clk,a,b,c;
  
  //clock generation
  always #5 clk = ~clk; 
  
  //generating a, b and c
  initial begin
    a=0; b=0;
    #15 a=1; b=0; c=0; //15
    #10 a=0; b=1; c=0; //25
    #10 a=0; b=1; c=0; //35
    #10 a=0; b=0; c=0; //45
    #10 a=0; b=1; c=0; //55
    #10 a=0; b=0; c=0; //65
    #10 a=0; b=0; c=0; //75
    #10 a=1; b=0; c=0; //85
    #10 a=0; b=1; c=0; //95
    #10 a=0; b=0; c=0; //105
    #10 a=0; b=1; c=0; //115
    #10 a=0; b=0; c=0; //125
    #10 a=0; b=1; c=0; //135
    #10 a=0; b=0; c=1; //145
    #10 a=0; b=0; c=0; //155
    // Wait for 10 time units before terminating the simulation
    #10;
    // End the simulation
    $finish;
  end
  
  //property includes a and b[->3] ##1 c using overlapped implication operator
  property p;
    // Property holds true when the a aseerted then b asserted 3 time at any clock then next clock c assert
    @(posedge clk) a |-> b[->3] ##1 c;
  endproperty
  
  //calling assert property
  a_1: assert property(p)
         $info("pass");
       else
         $info("fail");

  // Initial block to generate waveform dump for simulation
  initial begin
    $dumpfile("waveform.vcd");
    $dumpvars();
  end  
endmodule

assertion/repetition_operators/goto_repetition/waveform.vcd
$date
	Tue Oct 11 01:51:33 2022
$end

$version
	Synopsys VCS version Q-2020.03-SP2-8_Full64
$end

$timescale
	1s
$end

$comment Csum: 1 4ee04c1f6594c551 $end


$scope module goto_repetition $end
$var reg 1 ! a $end
$var reg 1 " b $end
$var reg 1 # c $end
$var reg 1 $ clk $end

$scope task _$$txp_pass_action_a_1 $end
$upscope $end


$scope task _$$txp_fail_action_a_1 $end
$upscope $end

$upscope $end

$enddefinitions $end

#0
$dumpvars
0!
0"
0#
0$
$end
#5
1$
#10
0$
#15
1!
1$
#20
0$
#25
0!
1"
1$
#30
0$
#35
1$
#40
0$
#45
0"
1$
#50
0$
#55
1"
1$
#60
0$
#65
0"
1$
#70
0$
#75
1$
#80
0$
#85
1!
1$
#90
0$
#95
0!
1"
1$
#100
0$
#105
0"
1$
#110
0$
#115
1"
1$
#120
0$
#125
0"
1$
#130
0$
#135
1"
1$
#140
0$
#145
0"
1#
1$
#150
0$
#155
0#
1$
