assertion/SVA_Methods/onehot0/onehot0.sv
module onehot0;  
bit clk,a;  
logic [4:0] b;  

always #5 clk = ~clk; //clock generation  

initial begin
  a=0; b=5'b00000;
  #15 a=1; b=5'b00100;  //15
  #10 a=0; b=5'b01000;  //25
  #10 a=1; b=5'b01000;  //35
  #10 a=0; b=5'b01000;  //45
  #10 a=1; b=5'b10000;  //55
  #10 a=0; b=5'b10000;  //65
  #10 a=1; b=5'b11000;  //75
  #10 a=0; b=5'b01100;  //85
  #10 a=1; b=5'b01100;  //95
  #10 a=0; b=5'b01000;  //105
  #10 a=1; b=5'b11100;  //115
  #10 a=0; b=5'b01000;  //125
  #10 a=1; b=5'b00000;  //135
  #10 a=1; b=5'b00100;  //145
  #10;
  $finish;
end

//property definition  
property p;  
  @(posedge clk) a |-> $onehot0(b);  
endproperty  

//calling assert property  
a_1: assert property(p)  
$info("Pass");  
else  
  $info("Fail");  

  initial begin
    $dumpfile("waveform.vcd");
    $dumpvars();
  end
  endmodule

assertion/SVA_Methods/onehot0/waveform.vcd
$date
	Tue Oct 11 02:07:27 2022
$end

$version
	Synopsys VCS version Q-2020.03-SP2-8_Full64
$end

$timescale
	1s
$end

$comment Csum: 1 d56406de437afe7b $end


$scope module onehot0 $end
$var reg 1 ! a $end
$var reg 5 " b [4:0] $end
$var reg 1 # clk $end

$scope task _$$txp______assert_a_1 $end
$upscope $end


$scope task _$$txp_pass_action_a_1 $end
$upscope $end


$scope task _$$txp_fail_action_a_1 $end
$upscope $end

$upscope $end

$enddefinitions $end

#0
$dumpvars
0!
0#
b00000 "
$end
#5
1#
#10
0#
#15
1!
b00100 "
1#
#20
0#
#25
0!
b01000 "
1#
#30
0#
#35
1!
1#
#40
0#
#45
0!
1#
#50
0#
#55
1!
b10000 "
1#
#60
0#
#65
0!
1#
#70
0#
#75
1!
b11000 "
1#
#80
0#
#85
0!
b01100 "
1#
#90
0#
#95
1!
1#
#100
0#
#105
0!
b01000 "
1#
#110
0#
#115
1!
b11100 "
1#
#120
0#
#125
0!
b01000 "
1#
#130
0#
#135
1!
b00000 "
1#
#140
0#
#145
b00100 "
1#
