assertion/SVA_Methods/fell/fell.sv
module fell;  
  //declared variable to generate diffrents values
  bit clk,a,b;  
  
  //clock generation
  always #5 clk = ~clk;   
  
  //generating a and b
  initial begin
    a=0; b=0;
    #15 a=1; b=0;  //15
    #10 a=0; b=1;  //25
    #10 a=1; b=0;  //35
    #10 a=0; b=0;  //45
    #10 a=1; b=1;  //55
    #10 a=0; b=0;  //65
    #10 a=1; b=1;  //75
    #10 a=1; b=0;  //85
    #10 a=1; b=0;  //95
    #10 a=0; b=0;  //105
    #10 a=1; b=0;  //115
    #10 a=0; b=0;  //125
    #10 a=1; b=0;  //135
    #10 a=1; b=0;  //145
    // Wait for 10 time units before terminating the simulation
    #10;
    // End the simulation
    $finish;
  end
  
  //property includes a and $fell(b) using overlapped implication operator
  property p;
    // Property holds true when the a aseerted and at the same clock edge b go 1 or unknown to low     
    @(posedge clk) a |-> $fell(b);  
  endproperty  
  
  //calling assert property
  a_1: assert property(p)
         $info("pass");
       else
         $info("fail");

  // Initial block to generate waveform dump for simulation
  initial begin
    $dumpfile("waveform.vcd");
    $dumpvars();
  end  
endmodule

assertion/SVA_Methods/fell/waveform.vcd
$date
	Sun Mar  2 18:23:56 2025
$end

$version
	Synopsys VCS version Q-2020.03-SP2-8_Full64
$end

$timescale
	1s
$end

$comment Csum: 1 d94ba7fefade0015 $end


$scope module fell $end
$var reg 1 ! a $end
$var reg 1 " clk $end
$var reg 1 # b $end

$scope task _$$txp______assert_a_1 $end
$upscope $end


$scope task _$$txp_pass_action_a_1 $end
$upscope $end


$scope task _$$txp_fail_action_a_1 $end
$upscope $end

$upscope $end

$enddefinitions $end

#0
$dumpvars
0!
0#
0"
$end
#5
1"
#10
0"
#15
1!
1"
#20
0"
#25
0!
1#
1"
#30
0"
#35
1!
0#
1"
#40
0"
#45
0!
1"
#50
0"
#55
1!
1#
1"
#60
0"
#65
0!
0#
1"
#70
0"
#75
1!
1#
1"
#80
0"
#85
0#
1"
#90
0"
#95
1"
#100
0"
#105
0!
1"
#110
0"
#115
1!
1"
#120
0"
#125
0!
1"
#130
0"
#135
1!
1"
